{
  "spdxVersion": "SPDX-2.3",
  "dataLicense": "CC0-1.0",
  "SPDXID": "SPDXRef-DOCUMENT",
  "name": "Order-Food",
  "documentNamespace": "https://anchore.com/syft/dir/Order-Food-4a796d99-ecd7-479e-a1f0-477928255e03",
  "creationInfo": {
    "licenseListVersion": "3.23",
    "creators": ["Organization: Anchore, Inc", "Tool: syft-1.0.1"],
    "created": "2024-07-05T04:04:47Z"
  },
  "packages": [
    {
      "name": "github.com/dgryski/go-minhash",
      "SPDXID": "SPDXRef-Package-go-module-github.com-dgryski-go-minhash-f235105d189336dc",
      "versionInfo": "v0.0.0-20170608043002-7fe510aff544",
      "supplier": "NOASSERTION",
      "downloadLocation": "NOASSERTION",
      "filesAnalyzed": false,
      "checksums": [
        {
          "algorithm": "SHA256",
          "checksumValue": "e7863fd86179d8c489e27eb71d6bcd0c546dced826eadab652b397eb5b2318a7"
        }
      ],
      "sourceInfo": "acquired package info from go module information: /spdx-sbom-generator",
      "licenseConcluded": "NOASSERTION",
      "licenseDeclared": "NOASSERTION",
      "copyrightText": "NOASSERTION",
      "externalRefs": [
        {
          "referenceCategory": "SECURITY",
          "referenceType": "cpe23Type",
          "referenceLocator": "cpe:2.3:a:dgryski:go-minhash:v0.0.0-20170608043002-7fe510aff544:*:*:*:*:*:*:*"
        },
        {
          "referenceCategory": "SECURITY",
          "referenceType": "cpe23Type",
          "referenceLocator": "cpe:2.3:a:dgryski:go_minhash:v0.0.0-20170608043002-7fe510aff544:*:*:*:*:*:*:*"
        },
        {
          "referenceCategory": "PACKAGE-MANAGER",
          "referenceType": "purl",
          "referenceLocator": "pkg:golang/github.com/dgryski/go-minhash@v0.0.0-20170608043002-7fe510aff544"
        }
      ]
    },
    {
      "name": "github.com/ekzhu/minhash-lsh",
      "SPDXID": "SPDXRef-Package-go-module-github.com-ekzhu-minhash-lsh-d5879d3235e12b2a",
      "versionInfo": "v0.0.0-20171225071031-5c06ee8586a1",
      "supplier": "NOASSERTION",
      "downloadLocation": "NOASSERTION",
      "filesAnalyzed": false,
      "checksums": [
        {
          "algorithm": "SHA256",
          "checksumValue": "ffb1bbabc48325dada8798c362a648f291858d2aa20b37d210ef8d82a282617d"
        }
      ],
      "sourceInfo": "acquired package info from go module information: /spdx-sbom-generator",
      "licenseConcluded": "NOASSERTION",
      "licenseDeclared": "NOASSERTION",
      "copyrightText": "NOASSERTION",
      "externalRefs": [
        {
          "referenceCategory": "SECURITY",
          "referenceType": "cpe23Type",
          "referenceLocator": "cpe:2.3:a:ekzhu:minhash-lsh:v0.0.0-20171225071031-5c06ee8586a1:*:*:*:*:*:*:*"
        },
        {
          "referenceCategory": "SECURITY",
          "referenceType": "cpe23Type",
          "referenceLocator": "cpe:2.3:a:ekzhu:minhash_lsh:v0.0.0-20171225071031-5c06ee8586a1:*:*:*:*:*:*:*"
        },
        {
          "referenceCategory": "PACKAGE-MANAGER",
          "referenceType": "purl",
          "referenceLocator": "pkg:golang/github.com/ekzhu/minhash-lsh@v0.0.0-20171225071031-5c06ee8586a1"
        }
      ]
    },
    {
      "name": "github.com/emirpasic/gods",
      "SPDXID": "SPDXRef-Package-go-module-github.com-emirpasic-gods-620854f412d13680",
      "versionInfo": "v1.12.0",
      "supplier": "NOASSERTION",
      "downloadLocation": "NOASSERTION",
      "filesAnalyzed": false,
      "checksums": [
        {
          "algorithm": "SHA256",
          "checksumValue": "4005083d2682bb81be3ce725c5ea9bdc5f963e974aa851a5c37ebec8ecc696b8"
        }
      ],
      "sourceInfo": "acquired package info from go module information: /spdx-sbom-generator",
      "licenseConcluded": "NOASSERTION",
      "licenseDeclared": "NOASSERTION",
      "copyrightText": "NOASSERTION",
      "externalRefs": [
        {
          "referenceCategory": "SECURITY",
          "referenceType": "cpe23Type",
          "referenceLocator": "cpe:2.3:a:emirpasic:gods:v1.12.0:*:*:*:*:*:*:*"
        },
        {
          "referenceCategory": "PACKAGE-MANAGER",
          "referenceType": "purl",
          "referenceLocator": "pkg:golang/github.com/emirpasic/gods@v1.12.0"
        }
      ]
    },
    {
      "name": "github.com/go-enry/go-license-detector/v4",
      "SPDXID": "SPDXRef-Package-go-module-github.com-go-enry-go-license-detector-v4-281d2e026f79d598",
      "versionInfo": "v4.2.0",
      "supplier": "NOASSERTION",
      "downloadLocation": "NOASSERTION",
      "filesAnalyzed": false,
      "checksums": [
        {
          "algorithm": "SHA256",
          "checksumValue": "c0ba9b12e83699a15a84b267f59014c6528185b8de376f4809a956f7297ff053"
        }
      ],
      "sourceInfo": "acquired package info from go module information: /spdx-sbom-generator",
      "licenseConcluded": "NOASSERTION",
      "licenseDeclared": "NOASSERTION",
      "copyrightText": "NOASSERTION",
      "externalRefs": [
        {
          "referenceCategory": "SECURITY",
          "referenceType": "cpe23Type",
          "referenceLocator": "cpe:2.3:a:go-enry:go-license-detector\\/v4:v4.2.0:*:*:*:*:*:*:*"
        },
        {
          "referenceCategory": "SECURITY",
          "referenceType": "cpe23Type",
          "referenceLocator": "cpe:2.3:a:go-enry:go_license_detector\\/v4:v4.2.0:*:*:*:*:*:*:*"
        },
        {
          "referenceCategory": "SECURITY",
          "referenceType": "cpe23Type",
          "referenceLocator": "cpe:2.3:a:go_enry:go-license-detector\\/v4:v4.2.0:*:*:*:*:*:*:*"
        },
        {
          "referenceCategory": "SECURITY",
          "referenceType": "cpe23Type",
          "referenceLocator": "cpe:2.3:a:go_enry:go_license_detector\\/v4:v4.2.0:*:*:*:*:*:*:*"
        },
        {
          "referenceCategory": "SECURITY",
          "referenceType": "cpe23Type",
          "referenceLocator": "cpe:2.3:a:go:go-license-detector\\/v4:v4.2.0:*:*:*:*:*:*:*"
        },
        {
          "referenceCategory": "SECURITY",
          "referenceType": "cpe23Type",
          "referenceLocator": "cpe:2.3:a:go:go_license_detector\\/v4:v4.2.0:*:*:*:*:*:*:*"
        },
        {
          "referenceCategory": "PACKAGE-MANAGER",
          "referenceType": "purl",
          "referenceLocator": "pkg:golang/github.com/go-enry/go-license-detector@v4.2.0#v4"
        }
      ]
    },
    {
      "name": "github.com/go-git/gcfg",
      "SPDXID": "SPDXRef-Package-go-module-github.com-go-git-gcfg-006ca919669e745e",
      "versionInfo": "v1.5.0",
      "supplier": "NOASSERTION",
      "downloadLocation": "NOASSERTION",
      "filesAnalyzed": false,
      "checksums": [
        {
          "algorithm": "SHA256",
          "checksumValue": "43956235f185f33160c8958fa98c00eea185a0c4c488199d96471f466a4831ae"
        }
      ],
      "sourceInfo": "acquired package info from go module information: /spdx-sbom-generator",
      "licenseConcluded": "NOASSERTION",
      "licenseDeclared": "NOASSERTION",
      "copyrightText": "NOASSERTION",
      "externalRefs": [
        {
          "referenceCategory": "SECURITY",
          "referenceType": "cpe23Type",
          "referenceLocator": "cpe:2.3:a:go-git:gcfg:v1.5.0:*:*:*:*:*:*:*"
        },
        {
          "referenceCategory": "SECURITY",
          "referenceType": "cpe23Type",
          "referenceLocator": "cpe:2.3:a:go_git:gcfg:v1.5.0:*:*:*:*:*:*:*"
        },
        {
          "referenceCategory": "SECURITY",
          "referenceType": "cpe23Type",
          "referenceLocator": "cpe:2.3:a:go:gcfg:v1.5.0:*:*:*:*:*:*:*"
        },
        {
          "referenceCategory": "PACKAGE-MANAGER",
          "referenceType": "purl",
          "referenceLocator": "pkg:golang/github.com/go-git/gcfg@v1.5.0"
        }
      ]
    },
    {
      "name": "github.com/go-git/go-billy/v5",
      "SPDXID": "SPDXRef-Package-go-module-github.com-go-git-go-billy-v5-5f54f6662b30641b",
      "versionInfo": "v5.0.0",
      "supplier": "NOASSERTION",
      "downloadLocation": "NOASSERTION",
      "filesAnalyzed": false,
      "checksums": [
        {
          "algorithm": "SHA256",
          "checksumValue": "ecd407bddf4556277c54be2a554326f1789f04afb6c42a19da54a4d1a811ac73"
        }
      ],
      "sourceInfo": "acquired package info from go module information: /spdx-sbom-generator",
      "licenseConcluded": "NOASSERTION",
      "licenseDeclared": "NOASSERTION",
      "copyrightText": "NOASSERTION",
      "externalRefs": [
        {
          "referenceCategory": "SECURITY",
          "referenceType": "cpe23Type",
          "referenceLocator": "cpe:2.3:a:go-git:go-billy\\/v5:v5.0.0:*:*:*:*:*:*:*"
        },
        {
          "referenceCategory": "SECURITY",
          "referenceType": "cpe23Type",
          "referenceLocator": "cpe:2.3:a:go-git:go_billy\\/v5:v5.0.0:*:*:*:*:*:*:*"
        },
        {
          "referenceCategory": "SECURITY",
          "referenceType": "cpe23Type",
          "referenceLocator": "cpe:2.3:a:go_git:go-billy\\/v5:v5.0.0:*:*:*:*:*:*:*"
        },
        {
          "referenceCategory": "SECURITY",
          "referenceType": "cpe23Type",
          "referenceLocator": "cpe:2.3:a:go_git:go_billy\\/v5:v5.0.0:*:*:*:*:*:*:*"
        },
        {
          "referenceCategory": "SECURITY",
          "referenceType": "cpe23Type",
          "referenceLocator": "cpe:2.3:a:go:go-billy\\/v5:v5.0.0:*:*:*:*:*:*:*"
        },
        {
          "referenceCategory": "SECURITY",
          "referenceType": "cpe23Type",
          "referenceLocator": "cpe:2.3:a:go:go_billy\\/v5:v5.0.0:*:*:*:*:*:*:*"
        },
        {
          "referenceCategory": "PACKAGE-MANAGER",
          "referenceType": "purl",
          "referenceLocator": "pkg:golang/github.com/go-git/go-billy@v5.0.0#v5"
        }
      ]
    },
    {
      "name": "github.com/go-git/go-git/v5",
      "SPDXID": "SPDXRef-Package-go-module-github.com-go-git-go-git-v5-a4e5d79c27e1958e",
      "versionInfo": "v5.1.0",
      "supplier": "NOASSERTION",
      "downloadLocation": "NOASSERTION",
      "filesAnalyzed": false,
      "checksums": [
        {
          "algorithm": "SHA256",
          "checksumValue": "1f1267f60fc4ede62f296dc59bb26de1e7bc2d77cf3a6fc7d5c743bbcbc4b2c9"
        }
      ],
      "sourceInfo": "acquired package info from go module information: /spdx-sbom-generator",
      "licenseConcluded": "NOASSERTION",
      "licenseDeclared": "NOASSERTION",
      "copyrightText": "NOASSERTION",
      "externalRefs": [
        {
          "referenceCategory": "SECURITY",
          "referenceType": "cpe23Type",
          "referenceLocator": "cpe:2.3:a:go-git:go-git\\/v5:v5.1.0:*:*:*:*:*:*:*"
        },
        {
          "referenceCategory": "SECURITY",
          "referenceType": "cpe23Type",
          "referenceLocator": "cpe:2.3:a:go-git:go_git\\/v5:v5.1.0:*:*:*:*:*:*:*"
        },
        {
          "referenceCategory": "SECURITY",
          "referenceType": "cpe23Type",
          "referenceLocator": "cpe:2.3:a:go_git:go-git\\/v5:v5.1.0:*:*:*:*:*:*:*"
        },
        {
          "referenceCategory": "SECURITY",
          "referenceType": "cpe23Type",
          "referenceLocator": "cpe:2.3:a:go_git:go_git\\/v5:v5.1.0:*:*:*:*:*:*:*"
        },
        {
          "referenceCategory": "SECURITY",
          "referenceType": "cpe23Type",
          "referenceLocator": "cpe:2.3:a:go:go-git\\/v5:v5.1.0:*:*:*:*:*:*:*"
        },
        {
          "referenceCategory": "SECURITY",
          "referenceType": "cpe23Type",
          "referenceLocator": "cpe:2.3:a:go:go_git\\/v5:v5.1.0:*:*:*:*:*:*:*"
        },
        {
          "referenceCategory": "PACKAGE-MANAGER",
          "referenceType": "purl",
          "referenceLocator": "pkg:golang/github.com/go-git/go-git@v5.1.0#v5"
        }
      ]
    },
    {
      "name": "github.com/google/uuid",
      "SPDXID": "SPDXRef-Package-go-module-github.com-google-uuid-34d87e640a660224",
      "versionInfo": "v1.2.0",
      "supplier": "NOASSERTION",
      "downloadLocation": "NOASSERTION",
      "filesAnalyzed": false,
      "checksums": [
        {
          "algorithm": "SHA256",
          "checksumValue": "a8962d5e72515a6a5eee6ff75e5ca1aec2eb11446a1d1336931ce8c57ab2503b"
        }
      ],
      "sourceInfo": "acquired package info from go module information: /spdx-sbom-generator",
      "licenseConcluded": "NOASSERTION",
      "licenseDeclared": "NOASSERTION",
      "copyrightText": "NOASSERTION",
      "externalRefs": [
        {
          "referenceCategory": "SECURITY",
          "referenceType": "cpe23Type",
          "referenceLocator": "cpe:2.3:a:google:uuid:v1.2.0:*:*:*:*:*:*:*"
        },
        {
          "referenceCategory": "PACKAGE-MANAGER",
          "referenceType": "purl",
          "referenceLocator": "pkg:golang/github.com/google/uuid@v1.2.0"
        }
      ]
    },
    {
      "name": "github.com/gorilla/mux",
      "SPDXID": "SPDXRef-Package-go-module-github.com-gorilla-mux-262a6f49c345087c",
      "versionInfo": "v1.8.0",
      "supplier": "NOASSERTION",
      "downloadLocation": "NOASSERTION",
      "filesAnalyzed": false,
      "sourceInfo": "acquired package info from go module information: /go.mod",
      "licenseConcluded": "NOASSERTION",
      "licenseDeclared": "NOASSERTION",
      "copyrightText": "NOASSERTION",
      "externalRefs": [
        {
          "referenceCategory": "SECURITY",
          "referenceType": "cpe23Type",
          "referenceLocator": "cpe:2.3:a:gorilla:mux:v1.8.0:*:*:*:*:*:*:*"
        },
        {
          "referenceCategory": "PACKAGE-MANAGER",
          "referenceType": "purl",
          "referenceLocator": "pkg:golang/github.com/gorilla/mux@v1.8.0"
        }
      ]
    },
    {
      "name": "github.com/hhatto/gorst",
      "SPDXID": "SPDXRef-Package-go-module-github.com-hhatto-gorst-c70b3f8db8382927",
      "versionInfo": "v0.0.0-20181029133204-ca9f730cac5b",
      "supplier": "NOASSERTION",
      "downloadLocation": "NOASSERTION",
      "filesAnalyzed": false,
      "checksums": [
        {
          "algorithm": "SHA256",
          "checksumValue": "25dbb6b5b031911a2e4882e9d846e9a2c21bf21e203bed90b99127dddf6c2807"
        }
      ],
      "sourceInfo": "acquired package info from go module information: /spdx-sbom-generator",
      "licenseConcluded": "NOASSERTION",
      "licenseDeclared": "NOASSERTION",
      "copyrightText": "NOASSERTION",
      "externalRefs": [
        {
          "referenceCategory": "SECURITY",
          "referenceType": "cpe23Type",
          "referenceLocator": "cpe:2.3:a:hhatto:gorst:v0.0.0-20181029133204-ca9f730cac5b:*:*:*:*:*:*:*"
        },
        {
          "referenceCategory": "PACKAGE-MANAGER",
          "referenceType": "purl",
          "referenceLocator": "pkg:golang/github.com/hhatto/gorst@v0.0.0-20181029133204-ca9f730cac5b"
        }
      ]
    },
    {
      "name": "github.com/imdario/mergo",
      "SPDXID": "SPDXRef-Package-go-module-github.com-imdario-mergo-8c011446289cf572",
      "versionInfo": "v0.3.9",
      "supplier": "NOASSERTION",
      "downloadLocation": "NOASSERTION",
      "filesAnalyzed": false,
      "checksums": [
        {
          "algorithm": "SHA256",
          "checksumValue": "51ab9a2e78960851d677e269f68084913063f153bff432a0dcf57754234c0c88"
        }
      ],
      "sourceInfo": "acquired package info from go module information: /spdx-sbom-generator",
      "licenseConcluded": "NOASSERTION",
      "licenseDeclared": "NOASSERTION",
      "copyrightText": "NOASSERTION",
      "externalRefs": [
        {
          "referenceCategory": "SECURITY",
          "referenceType": "cpe23Type",
          "referenceLocator": "cpe:2.3:a:imdario:mergo:v0.3.9:*:*:*:*:*:*:*"
        },
        {
          "referenceCategory": "PACKAGE-MANAGER",
          "referenceType": "purl",
          "referenceLocator": "pkg:golang/github.com/imdario/mergo@v0.3.9"
        }
      ]
    },
    {
      "name": "github.com/jbenet/go-context",
      "SPDXID": "SPDXRef-Package-go-module-github.com-jbenet-go-context-d447fb06434976d8",
      "versionInfo": "v0.0.0-20150711004518-d14ea06fba99",
      "supplier": "NOASSERTION",
      "downloadLocation": "NOASSERTION",
      "filesAnalyzed": false,
      "checksums": [
        {
          "algorithm": "SHA256",
          "checksumValue": "05048578f03545624e968707e85c72f0c9b00edfb25506142ca7cdd11a1337c0"
        }
      ],
      "sourceInfo": "acquired package info from go module information: /spdx-sbom-generator",
      "licenseConcluded": "NOASSERTION",
      "licenseDeclared": "NOASSERTION",
      "copyrightText": "NOASSERTION",
      "externalRefs": [
        {
          "referenceCategory": "SECURITY",
          "referenceType": "cpe23Type",
          "referenceLocator": "cpe:2.3:a:jbenet:go-context:v0.0.0-20150711004518-d14ea06fba99:*:*:*:*:*:*:*"
        },
        {
          "referenceCategory": "SECURITY",
          "referenceType": "cpe23Type",
          "referenceLocator": "cpe:2.3:a:jbenet:go_context:v0.0.0-20150711004518-d14ea06fba99:*:*:*:*:*:*:*"
        },
        {
          "referenceCategory": "PACKAGE-MANAGER",
          "referenceType": "purl",
          "referenceLocator": "pkg:golang/github.com/jbenet/go-context@v0.0.0-20150711004518-d14ea06fba99"
        }
      ]
    },
    {
      "name": "github.com/jdkato/prose",
      "SPDXID": "SPDXRef-Package-go-module-github.com-jdkato-prose-b92485d836034044",
      "versionInfo": "v1.1.0",
      "supplier": "NOASSERTION",
      "downloadLocation": "NOASSERTION",
      "filesAnalyzed": false,
      "checksums": [
        {
          "algorithm": "SHA256",
          "checksumValue": "2e9be60c6c1b2864e07421f76bc5492f9eacafba7fc0e14fc3f47894ce0f7c58"
        }
      ],
      "sourceInfo": "acquired package info from go module information: /spdx-sbom-generator",
      "licenseConcluded": "NOASSERTION",
      "licenseDeclared": "NOASSERTION",
      "copyrightText": "NOASSERTION",
      "externalRefs": [
        {
          "referenceCategory": "SECURITY",
          "referenceType": "cpe23Type",
          "referenceLocator": "cpe:2.3:a:jdkato:prose:v1.1.0:*:*:*:*:*:*:*"
        },
        {
          "referenceCategory": "PACKAGE-MANAGER",
          "referenceType": "purl",
          "referenceLocator": "pkg:golang/github.com/jdkato/prose@v1.1.0"
        }
      ]
    },
    {
      "name": "github.com/kevinburke/ssh_config",
      "SPDXID": "SPDXRef-Package-go-module-github.com-kevinburke-ssh-config-5a02a9e1a3a903c2",
      "versionInfo": "v0.0.0-20190725054713-01f96b0aa0cd",
      "supplier": "NOASSERTION",
      "downloadLocation": "NOASSERTION",
      "filesAnalyzed": false,
      "checksums": [
        {
          "algorithm": "SHA256",
          "checksumValue": "0a87a4c1d874bf6c2d1a9f469b3d597b779544058930ba24bcddd08ddcc21cb6"
        }
      ],
      "sourceInfo": "acquired package info from go module information: /spdx-sbom-generator",
      "licenseConcluded": "NOASSERTION",
      "licenseDeclared": "NOASSERTION",
      "copyrightText": "NOASSERTION",
      "externalRefs": [
        {
          "referenceCategory": "SECURITY",
          "referenceType": "cpe23Type",
          "referenceLocator": "cpe:2.3:a:kevinburke:ssh-config:v0.0.0-20190725054713-01f96b0aa0cd:*:*:*:*:*:*:*"
        },
        {
          "referenceCategory": "SECURITY",
          "referenceType": "cpe23Type",
          "referenceLocator": "cpe:2.3:a:kevinburke:ssh_config:v0.0.0-20190725054713-01f96b0aa0cd:*:*:*:*:*:*:*"
        },
        {
          "referenceCategory": "PACKAGE-MANAGER",
          "referenceType": "purl",
          "referenceLocator": "pkg:golang/github.com/kevinburke/ssh_config@v0.0.0-20190725054713-01f96b0aa0cd"
        }
      ]
    },
    {
      "name": "github.com/mitchellh/go-homedir",
      "SPDXID": "SPDXRef-Package-go-module-github.com-mitchellh-go-homedir-34ce0104f9648738",
      "versionInfo": "v1.1.0",
      "supplier": "NOASSERTION",
      "downloadLocation": "NOASSERTION",
      "filesAnalyzed": false,
      "checksums": [
        {
          "algorithm": "SHA256",
          "checksumValue": "96e905f738971710c53e4035becaf9ce97355ee3c39ffc059edab9986fb81346"
        }
      ],
      "sourceInfo": "acquired package info from go module information: /spdx-sbom-generator",
      "licenseConcluded": "NOASSERTION",
      "licenseDeclared": "NOASSERTION",
      "copyrightText": "NOASSERTION",
      "externalRefs": [
        {
          "referenceCategory": "SECURITY",
          "referenceType": "cpe23Type",
          "referenceLocator": "cpe:2.3:a:mitchellh:go-homedir:v1.1.0:*:*:*:*:*:*:*"
        },
        {
          "referenceCategory": "SECURITY",
          "referenceType": "cpe23Type",
          "referenceLocator": "cpe:2.3:a:mitchellh:go_homedir:v1.1.0:*:*:*:*:*:*:*"
        },
        {
          "referenceCategory": "PACKAGE-MANAGER",
          "referenceType": "purl",
          "referenceLocator": "pkg:golang/github.com/mitchellh/go-homedir@v1.1.0"
        }
      ]
    },
    {
      "name": "github.com/montanaflynn/stats",
      "SPDXID": "SPDXRef-Package-go-module-github.com-montanaflynn-stats-d91fed62197fca1c",
      "versionInfo": "v0.0.0-20151014174947-eeaced052adb",
      "supplier": "NOASSERTION",
      "downloadLocation": "NOASSERTION",
      "filesAnalyzed": false,
      "checksums": [
        {
          "algorithm": "SHA256",
          "checksumValue": "6ec8cd003b231ead208d4eca3bbcf0a17e64dc7b4575fe930f30779dc979894b"
        }
      ],
      "sourceInfo": "acquired package info from go module information: /spdx-sbom-generator",
      "licenseConcluded": "NOASSERTION",
      "licenseDeclared": "NOASSERTION",
      "copyrightText": "NOASSERTION",
      "externalRefs": [
        {
          "referenceCategory": "SECURITY",
          "referenceType": "cpe23Type",
          "referenceLocator": "cpe:2.3:a:montanaflynn:stats:v0.0.0-20151014174947-eeaced052adb:*:*:*:*:*:*:*"
        },
        {
          "referenceCategory": "PACKAGE-MANAGER",
          "referenceType": "purl",
          "referenceLocator": "pkg:golang/github.com/montanaflynn/stats@v0.0.0-20151014174947-eeaced052adb"
        }
      ]
    },
    {
      "name": "github.com/pkg/errors",
      "SPDXID": "SPDXRef-Package-go-module-github.com-pkg-errors-ea692f11be449967",
      "versionInfo": "v0.9.1",
      "supplier": "NOASSERTION",
      "downloadLocation": "NOASSERTION",
      "filesAnalyzed": false,
      "checksums": [
        {
          "algorithm": "SHA256",
          "checksumValue": "14404bc75cd2db5e28c298f2eeab017a2c5b51192e850030acae54c0b193c2de"
        }
      ],
      "sourceInfo": "acquired package info from go module information: /spdx-sbom-generator",
      "licenseConcluded": "NOASSERTION",
      "licenseDeclared": "NOASSERTION",
      "copyrightText": "NOASSERTION",
      "externalRefs": [
        {
          "referenceCategory": "SECURITY",
          "referenceType": "cpe23Type",
          "referenceLocator": "cpe:2.3:a:pkg:errors:v0.9.1:*:*:*:*:*:*:*"
        },
        {
          "referenceCategory": "PACKAGE-MANAGER",
          "referenceType": "purl",
          "referenceLocator": "pkg:golang/github.com/pkg/errors@v0.9.1"
        }
      ]
    },
    {
      "name": "github.com/russross/blackfriday/v2",
      "SPDXID": "SPDXRef-Package-go-module-github.com-russross-blackfriday-v2-ef70a7c214258c18",
      "versionInfo": "v2.0.1",
      "supplier": "NOASSERTION",
      "downloadLocation": "NOASSERTION",
      "filesAnalyzed": false,
      "checksums": [
        {
          "algorithm": "SHA256",
          "checksumValue": "94fa9502d7be1ee1cd7e127fd0b0bdf04496473f1a7f2f6d33fd112bc9bda3e4"
        }
      ],
      "sourceInfo": "acquired package info from go module information: /spdx-sbom-generator",
      "licenseConcluded": "NOASSERTION",
      "licenseDeclared": "NOASSERTION",
      "copyrightText": "NOASSERTION",
      "externalRefs": [
        {
          "referenceCategory": "SECURITY",
          "referenceType": "cpe23Type",
          "referenceLocator": "cpe:2.3:a:russross:blackfriday\\/v2:v2.0.1:*:*:*:*:*:*:*"
        },
        {
          "referenceCategory": "PACKAGE-MANAGER",
          "referenceType": "purl",
          "referenceLocator": "pkg:golang/github.com/russross/blackfriday@v2.0.1#v2"
        }
      ]
    },
    {
      "name": "github.com/sergi/go-diff",
      "SPDXID": "SPDXRef-Package-go-module-github.com-sergi-go-diff-8a86c996523c22af",
      "versionInfo": "v1.1.0",
      "supplier": "NOASSERTION",
      "downloadLocation": "NOASSERTION",
      "filesAnalyzed": false,
      "checksums": [
        {
          "algorithm": "SHA256",
          "checksumValue": "c1ef0f5540b7144dae61fa1d287fe70473127ad49f1c347ab1c19d062f9eae1d"
        }
      ],
      "sourceInfo": "acquired package info from go module information: /spdx-sbom-generator",
      "licenseConcluded": "NOASSERTION",
      "licenseDeclared": "NOASSERTION",
      "copyrightText": "NOASSERTION",
      "externalRefs": [
        {
          "referenceCategory": "SECURITY",
          "referenceType": "cpe23Type",
          "referenceLocator": "cpe:2.3:a:sergi:go-diff:v1.1.0:*:*:*:*:*:*:*"
        },
        {
          "referenceCategory": "SECURITY",
          "referenceType": "cpe23Type",
          "referenceLocator": "cpe:2.3:a:sergi:go_diff:v1.1.0:*:*:*:*:*:*:*"
        },
        {
          "referenceCategory": "PACKAGE-MANAGER",
          "referenceType": "purl",
          "referenceLocator": "pkg:golang/github.com/sergi/go-diff@v1.1.0"
        }
      ]
    },
    {
      "name": "github.com/shogo82148/go-shuffle",
      "SPDXID": "SPDXRef-Package-go-module-github.com-shogo82148-go-shuffle-02ae862873d6521b",
      "versionInfo": "v0.0.0-20170808115208-59829097ff3b",
      "supplier": "NOASSERTION",
      "downloadLocation": "NOASSERTION",
      "filesAnalyzed": false,
      "checksums": [
        {
          "algorithm": "SHA256",
          "checksumValue": "548d6efa8d8a64f679021b8fa5763424176940f9e44f1e837795c984affd3181"
        }
      ],
      "sourceInfo": "acquired package info from go module information: /spdx-sbom-generator",
      "licenseConcluded": "NOASSERTION",
      "licenseDeclared": "NOASSERTION",
      "copyrightText": "NOASSERTION",
      "externalRefs": [
        {
          "referenceCategory": "SECURITY",
          "referenceType": "cpe23Type",
          "referenceLocator": "cpe:2.3:a:shogo82148:go-shuffle:v0.0.0-20170808115208-59829097ff3b:*:*:*:*:*:*:*"
        },
        {
          "referenceCategory": "SECURITY",
          "referenceType": "cpe23Type",
          "referenceLocator": "cpe:2.3:a:shogo82148:go_shuffle:v0.0.0-20170808115208-59829097ff3b:*:*:*:*:*:*:*"
        },
        {
          "referenceCategory": "PACKAGE-MANAGER",
          "referenceType": "purl",
          "referenceLocator": "pkg:golang/github.com/shogo82148/go-shuffle@v0.0.0-20170808115208-59829097ff3b"
        }
      ]
    },
    {
      "name": "github.com/shurcooL/sanitized_anchor_name",
      "SPDXID": "SPDXRef-Package-go-module-github.com-shurcooL-sanitized-anchor-name-0865d03729cd7ea5",
      "versionInfo": "v1.0.0",
      "supplier": "NOASSERTION",
      "downloadLocation": "NOASSERTION",
      "filesAnalyzed": false,
      "checksums": [
        {
          "algorithm": "SHA256",
          "checksumValue": "3dd9a808eeb0bdbb3eef2ac9c8c391b78fc1998e486322704bf90e896c7c987a"
        }
      ],
      "sourceInfo": "acquired package info from go module information: /spdx-sbom-generator",
      "licenseConcluded": "NOASSERTION",
      "licenseDeclared": "NOASSERTION",
      "copyrightText": "NOASSERTION",
      "externalRefs": [
        {
          "referenceCategory": "SECURITY",
          "referenceType": "cpe23Type",
          "referenceLocator": "cpe:2.3:a:shurcooL:sanitized-anchor-name:v1.0.0:*:*:*:*:*:*:*"
        },
        {
          "referenceCategory": "SECURITY",
          "referenceType": "cpe23Type",
          "referenceLocator": "cpe:2.3:a:shurcooL:sanitized_anchor_name:v1.0.0:*:*:*:*:*:*:*"
        },
        {
          "referenceCategory": "PACKAGE-MANAGER",
          "referenceType": "purl",
          "referenceLocator": "pkg:golang/github.com/shurcooL/sanitized_anchor_name@v1.0.0"
        }
      ]
    },
    {
      "name": "github.com/sirupsen/logrus",
      "SPDXID": "SPDXRef-Package-go-module-github.com-sirupsen-logrus-430a03d7f3ae0782",
      "versionInfo": "v1.8.1",
      "supplier": "NOASSERTION",
      "downloadLocation": "NOASSERTION",
      "filesAnalyzed": false,
      "checksums": [
        {
          "algorithm": "SHA256",
          "checksumValue": "7492ae1e0aa4d4d35096aa00e814e533559ff43387dcd063432bb487df806591"
        }
      ],
      "sourceInfo": "acquired package info from go module information: /spdx-sbom-generator",
      "licenseConcluded": "NOASSERTION",
      "licenseDeclared": "NOASSERTION",
      "copyrightText": "NOASSERTION",
      "externalRefs": [
        {
          "referenceCategory": "SECURITY",
          "referenceType": "cpe23Type",
          "referenceLocator": "cpe:2.3:a:sirupsen:logrus:v1.8.1:*:*:*:*:*:*:*"
        },
        {
          "referenceCategory": "PACKAGE-MANAGER",
          "referenceType": "purl",
          "referenceLocator": "pkg:golang/github.com/sirupsen/logrus@v1.8.1"
        }
      ]
    },
    {
      "name": "github.com/spf13/cobra",
      "SPDXID": "SPDXRef-Package-go-module-github.com-spf13-cobra-681f517529653d5c",
      "versionInfo": "v1.1.3",
      "supplier": "NOASSERTION",
      "downloadLocation": "NOASSERTION",
      "filesAnalyzed": false,
      "checksums": [
        {
          "algorithm": "SHA256",
          "checksumValue": "c6085b7ea3e4c73c4fdc2fdfde7e4376901b74a2e3e19138056408dfada5e773"
        }
      ],
      "sourceInfo": "acquired package info from go module information: /spdx-sbom-generator",
      "licenseConcluded": "NOASSERTION",
      "licenseDeclared": "NOASSERTION",
      "copyrightText": "NOASSERTION",
      "externalRefs": [
        {
          "referenceCategory": "SECURITY",
          "referenceType": "cpe23Type",
          "referenceLocator": "cpe:2.3:a:spf13:cobra:v1.1.3:*:*:*:*:*:*:*"
        },
        {
          "referenceCategory": "PACKAGE-MANAGER",
          "referenceType": "purl",
          "referenceLocator": "pkg:golang/github.com/spf13/cobra@v1.1.3"
        }
      ]
    },
    {
      "name": "github.com/spf13/pflag",
      "SPDXID": "SPDXRef-Package-go-module-github.com-spf13-pflag-2c0d2f578cfd75ad",
      "versionInfo": "v1.0.5",
      "supplier": "NOASSERTION",
      "downloadLocation": "NOASSERTION",
      "filesAnalyzed": false,
      "checksums": [
        {
          "algorithm": "SHA256",
          "checksumValue": "8b2f951543823f56bef3216da3f76b836089e6ed3246807b7d9c370cabff2570"
        }
      ],
      "sourceInfo": "acquired package info from go module information: /spdx-sbom-generator",
      "licenseConcluded": "NOASSERTION",
      "licenseDeclared": "NOASSERTION",
      "copyrightText": "NOASSERTION",
      "externalRefs": [
        {
          "referenceCategory": "SECURITY",
          "referenceType": "cpe23Type",
          "referenceLocator": "cpe:2.3:a:spf13:pflag:v1.0.5:*:*:*:*:*:*:*"
        },
        {
          "referenceCategory": "PACKAGE-MANAGER",
          "referenceType": "purl",
          "referenceLocator": "pkg:golang/github.com/spf13/pflag@v1.0.5"
        }
      ]
    },
    {
      "name": "github.com/vifraa/gopom",
      "SPDXID": "SPDXRef-Package-go-module-github.com-vifraa-gopom-9bba428b329e73c0",
      "versionInfo": "v0.1.0",
      "supplier": "NOASSERTION",
      "downloadLocation": "NOASSERTION",
      "filesAnalyzed": false,
      "checksums": [
        {
          "algorithm": "SHA256",
          "checksumValue": "bfcf7b795c5fea57e59045f33e629ba386215f6a12fcb1a3cfb72a8d69d29825"
        }
      ],
      "sourceInfo": "acquired package info from go module information: /spdx-sbom-generator",
      "licenseConcluded": "NOASSERTION",
      "licenseDeclared": "NOASSERTION",
      "copyrightText": "NOASSERTION",
      "externalRefs": [
        {
          "referenceCategory": "SECURITY",
          "referenceType": "cpe23Type",
          "referenceLocator": "cpe:2.3:a:vifraa:gopom:v0.1.0:*:*:*:*:*:*:*"
        },
        {
          "referenceCategory": "PACKAGE-MANAGER",
          "referenceType": "purl",
          "referenceLocator": "pkg:golang/github.com/vifraa/gopom@v0.1.0"
        }
      ]
    },
    {
      "name": "github.com/xanzy/ssh-agent",
      "SPDXID": "SPDXRef-Package-go-module-github.com-xanzy-ssh-agent-326f578af4718053",
      "versionInfo": "v0.2.1",
      "supplier": "NOASSERTION",
      "downloadLocation": "NOASSERTION",
      "filesAnalyzed": false,
      "checksums": [
        {
          "algorithm": "SHA256",
          "checksumValue": "4c26e2a5340bd898a20a9ac15b1f5fac9d9e2650984f4d0d99cb6b1f1540afbd"
        }
      ],
      "sourceInfo": "acquired package info from go module information: /spdx-sbom-generator",
      "licenseConcluded": "NOASSERTION",
      "licenseDeclared": "NOASSERTION",
      "copyrightText": "NOASSERTION",
      "externalRefs": [
        {
          "referenceCategory": "SECURITY",
          "referenceType": "cpe23Type",
          "referenceLocator": "cpe:2.3:a:xanzy:ssh-agent:v0.2.1:*:*:*:*:*:*:*"
        },
        {
          "referenceCategory": "SECURITY",
          "referenceType": "cpe23Type",
          "referenceLocator": "cpe:2.3:a:xanzy:ssh_agent:v0.2.1:*:*:*:*:*:*:*"
        },
        {
          "referenceCategory": "PACKAGE-MANAGER",
          "referenceType": "purl",
          "referenceLocator": "pkg:golang/github.com/xanzy/ssh-agent@v0.2.1"
        }
      ]
    },
    {
      "name": "goProject",
      "SPDXID": "SPDXRef-Package-go-module-goProject-eff3e671e31c66c7",
      "versionInfo": "v0.0.0-20220628093626-00c67e62b377",
      "supplier": "NOASSERTION",
      "downloadLocation": "NOASSERTION",
      "filesAnalyzed": false,
      "sourceInfo": "acquired package info from go module information: /goProject",
      "licenseConcluded": "NOASSERTION",
      "licenseDeclared": "NOASSERTION",
      "copyrightText": "NOASSERTION",
      "externalRefs": [
        {
          "referenceCategory": "PACKAGE-MANAGER",
          "referenceType": "purl",
          "referenceLocator": "pkg:golang/goProject@v0.0.0-20220628093626-00c67e62b377"
        }
      ]
    },
    {
      "name": "golang.org/x/crypto",
      "SPDXID": "SPDXRef-Package-go-module-golang.org-x-crypto-993511094aee627b",
      "versionInfo": "v0.0.0-20200302210943-78000ba7a073",
      "supplier": "NOASSERTION",
      "downloadLocation": "NOASSERTION",
      "filesAnalyzed": false,
      "checksums": [
        {
          "algorithm": "SHA256",
          "checksumValue": "c4c3ce8fa3f3e948a9535c172e4aedaa91db474015167c8f110abfc115b3f653"
        }
      ],
      "sourceInfo": "acquired package info from go module information: /spdx-sbom-generator",
      "licenseConcluded": "NOASSERTION",
      "licenseDeclared": "NOASSERTION",
      "copyrightText": "NOASSERTION",
      "externalRefs": [
        {
          "referenceCategory": "SECURITY",
          "referenceType": "cpe23Type",
          "referenceLocator": "cpe:2.3:a:golang:x\\/crypto:v0.0.0-20200302210943-78000ba7a073:*:*:*:*:*:*:*"
        },
        {
          "referenceCategory": "PACKAGE-MANAGER",
          "referenceType": "purl",
          "referenceLocator": "pkg:golang/golang.org/x/crypto@v0.0.0-20200302210943-78000ba7a073"
        }
      ]
    },
    {
      "name": "golang.org/x/exp",
      "SPDXID": "SPDXRef-Package-go-module-golang.org-x-exp-f09380142cf00a77",
      "versionInfo": "v0.0.0-20191030013958-a1ab85dbe136",
      "supplier": "NOASSERTION",
      "downloadLocation": "NOASSERTION",
      "filesAnalyzed": false,
      "checksums": [
        {
          "algorithm": "SHA256",
          "checksumValue": "0358064b1e7c2c01951d452c39fec8891d2ef176fa5b9d604707c306191d71ac"
        }
      ],
      "sourceInfo": "acquired package info from go module information: /spdx-sbom-generator",
      "licenseConcluded": "NOASSERTION",
      "licenseDeclared": "NOASSERTION",
      "copyrightText": "NOASSERTION",
      "externalRefs": [
        {
          "referenceCategory": "SECURITY",
          "referenceType": "cpe23Type",
          "referenceLocator": "cpe:2.3:a:golang:x\\/exp:v0.0.0-20191030013958-a1ab85dbe136:*:*:*:*:*:*:*"
        },
        {
          "referenceCategory": "PACKAGE-MANAGER",
          "referenceType": "purl",
          "referenceLocator": "pkg:golang/golang.org/x/exp@v0.0.0-20191030013958-a1ab85dbe136"
        }
      ]
    },
    {
      "name": "golang.org/x/net",
      "SPDXID": "SPDXRef-Package-go-module-golang.org-x-net-861d0f1c98cedfc8",
      "versionInfo": "v0.0.0-20200301022130-244492dfa37a",
      "supplier": "NOASSERTION",
      "downloadLocation": "NOASSERTION",
      "filesAnalyzed": false,
      "checksums": [
        {
          "algorithm": "SHA256",
          "checksumValue": "1ae48f61b673079fdd70b342c0b40bb20de86c226d5fd2098695e4bd8ee4ce4d"
        }
      ],
      "sourceInfo": "acquired package info from go module information: /spdx-sbom-generator",
      "licenseConcluded": "NOASSERTION",
      "licenseDeclared": "NOASSERTION",
      "copyrightText": "NOASSERTION",
      "externalRefs": [
        {
          "referenceCategory": "SECURITY",
          "referenceType": "cpe23Type",
          "referenceLocator": "cpe:2.3:a:golang:x\\/net:v0.0.0-20200301022130-244492dfa37a:*:*:*:*:*:*:*"
        },
        {
          "referenceCategory": "PACKAGE-MANAGER",
          "referenceType": "purl",
          "referenceLocator": "pkg:golang/golang.org/x/net@v0.0.0-20200301022130-244492dfa37a"
        }
      ]
    },
    {
      "name": "golang.org/x/sys",
      "SPDXID": "SPDXRef-Package-go-module-golang.org-x-sys-735078e5f86246b0",
      "versionInfo": "v0.0.0-20200302150141-5c8b2ff67527",
      "supplier": "NOASSERTION",
      "downloadLocation": "NOASSERTION",
      "filesAnalyzed": false,
      "checksums": [
        {
          "algorithm": "SHA256",
          "checksumValue": "b9855543d58ffc3b3644e85c6863de21d56ad1121754bc2c1e59ef27e713d52a"
        }
      ],
      "sourceInfo": "acquired package info from go module information: /spdx-sbom-generator",
      "licenseConcluded": "NOASSERTION",
      "licenseDeclared": "NOASSERTION",
      "copyrightText": "NOASSERTION",
      "externalRefs": [
        {
          "referenceCategory": "SECURITY",
          "referenceType": "cpe23Type",
          "referenceLocator": "cpe:2.3:a:golang:x\\/sys:v0.0.0-20200302150141-5c8b2ff67527:*:*:*:*:*:*:*"
        },
        {
          "referenceCategory": "PACKAGE-MANAGER",
          "referenceType": "purl",
          "referenceLocator": "pkg:golang/golang.org/x/sys@v0.0.0-20200302150141-5c8b2ff67527"
        }
      ]
    },
    {
      "name": "golang.org/x/text",
      "SPDXID": "SPDXRef-Package-go-module-golang.org-x-text-08717222b39fbd54",
      "versionInfo": "v0.3.6",
      "supplier": "NOASSERTION",
      "downloadLocation": "NOASSERTION",
      "filesAnalyzed": false,
      "checksums": [
        {
          "algorithm": "SHA256",
          "checksumValue": "691631371bfa886425c956999a4e998181036be260d7c0f179b3d2adde9b8353"
        }
      ],
      "sourceInfo": "acquired package info from go module information: /spdx-sbom-generator",
      "licenseConcluded": "NOASSERTION",
      "licenseDeclared": "NOASSERTION",
      "copyrightText": "NOASSERTION",
      "externalRefs": [
        {
          "referenceCategory": "SECURITY",
          "referenceType": "cpe23Type",
          "referenceLocator": "cpe:2.3:a:golang:x\\/text:v0.3.6:*:*:*:*:*:*:*"
        },
        {
          "referenceCategory": "PACKAGE-MANAGER",
          "referenceType": "purl",
          "referenceLocator": "pkg:golang/golang.org/x/text@v0.3.6"
        }
      ]
    },
    {
      "name": "gonum.org/v1/gonum",
      "SPDXID": "SPDXRef-Package-go-module-gonum.org-v1-gonum-9b38fa3d8d7e4329",
      "versionInfo": "v0.7.0",
      "supplier": "NOASSERTION",
      "downloadLocation": "NOASSERTION",
      "filesAnalyzed": false,
      "checksums": [
        {
          "algorithm": "SHA256",
          "checksumValue": "1dd92cd0bd218339d92c6f67cd76fcbd9d2b46fa8dbc0720029f38cbb330920c"
        }
      ],
      "sourceInfo": "acquired package info from go module information: /spdx-sbom-generator",
      "licenseConcluded": "NOASSERTION",
      "licenseDeclared": "NOASSERTION",
      "copyrightText": "NOASSERTION",
      "externalRefs": [
        {
          "referenceCategory": "SECURITY",
          "referenceType": "cpe23Type",
          "referenceLocator": "cpe:2.3:a:v1:gonum:v0.7.0:*:*:*:*:*:*:*"
        },
        {
          "referenceCategory": "PACKAGE-MANAGER",
          "referenceType": "purl",
          "referenceLocator": "pkg:golang/gonum.org/v1/gonum@v0.7.0"
        }
      ]
    },
    {
      "name": "gopkg.in/neurosnap/sentences.v1",
      "SPDXID": "SPDXRef-Package-go-module-gopkg.in-neurosnap-sentences.v1-a35e8fc47f3bcc48",
      "versionInfo": "v1.0.6",
      "supplier": "NOASSERTION",
      "downloadLocation": "NOASSERTION",
      "filesAnalyzed": false,
      "checksums": [
        {
          "algorithm": "SHA256",
          "checksumValue": "bfb125c8fd36d2211940e3722e57777c720b1d638fb3e9edcee41334f92e97c1"
        }
      ],
      "sourceInfo": "acquired package info from go module information: /spdx-sbom-generator",
      "licenseConcluded": "NOASSERTION",
      "licenseDeclared": "NOASSERTION",
      "copyrightText": "NOASSERTION",
      "externalRefs": [
        {
          "referenceCategory": "PACKAGE-MANAGER",
          "referenceType": "purl",
          "referenceLocator": "pkg:golang/gopkg.in/neurosnap/sentences.v1@v1.0.6"
        }
      ]
    },
    {
      "name": "gopkg.in/warnings.v0",
      "SPDXID": "SPDXRef-Package-go-module-gopkg.in-warnings.v0-e924fe56aa559902",
      "versionInfo": "v0.1.2",
      "supplier": "NOASSERTION",
      "downloadLocation": "NOASSERTION",
      "filesAnalyzed": false,
      "checksums": [
        {
          "algorithm": "SHA256",
          "checksumValue": "c055d56c563c0d8e7fc4e7b510289674a0b3665c60b2171854d9011ecb4044c1"
        }
      ],
      "sourceInfo": "acquired package info from go module information: /spdx-sbom-generator",
      "licenseConcluded": "NOASSERTION",
      "licenseDeclared": "NOASSERTION",
      "copyrightText": "NOASSERTION",
      "externalRefs": [
        {
          "referenceCategory": "PACKAGE-MANAGER",
          "referenceType": "purl",
          "referenceLocator": "pkg:golang/gopkg.in/warnings.v0@v0.1.2"
        }
      ]
    },
    {
      "name": "spdx-sbom-generator",
      "SPDXID": "SPDXRef-Package-go-module-spdx-sbom-generator-d0a2de88739abf02",
      "versionInfo": "v0.0.10",
      "supplier": "NOASSERTION",
      "downloadLocation": "NOASSERTION",
      "filesAnalyzed": false,
      "sourceInfo": "acquired package info from go module information: /spdx-sbom-generator",
      "licenseConcluded": "NOASSERTION",
      "licenseDeclared": "NOASSERTION",
      "copyrightText": "NOASSERTION",
      "externalRefs": [
        {
          "referenceCategory": "PACKAGE-MANAGER",
          "referenceType": "purl",
          "referenceLocator": "pkg:golang/spdx-sbom-generator@v0.0.10"
        }
      ]
    },
    {
      "name": "stdlib",
      "SPDXID": "SPDXRef-Package-go-module-stdlib-9d1e6fab90778ac1",
      "versionInfo": "go1.13.1",
      "supplier": "NOASSERTION",
      "downloadLocation": "NOASSERTION",
      "filesAnalyzed": false,
      "sourceInfo": "acquired package info from go module information: /spdx-sbom-generator",
      "licenseConcluded": "NOASSERTION",
      "licenseDeclared": "BSD-3-Clause",
      "copyrightText": "NOASSERTION",
      "externalRefs": [
        {
          "referenceCategory": "SECURITY",
          "referenceType": "cpe23Type",
          "referenceLocator": "cpe:2.3:a:golang:go:1.13.1:-:*:*:*:*:*:*"
        },
        {
          "referenceCategory": "PACKAGE-MANAGER",
          "referenceType": "purl",
          "referenceLocator": "pkg:golang/stdlib@1.13.1"
        }
      ]
    },
    {
      "name": "stdlib",
      "SPDXID": "SPDXRef-Package-go-module-stdlib-57ad8100ec4e1576",
      "versionInfo": "go1.18.1",
      "supplier": "NOASSERTION",
      "downloadLocation": "NOASSERTION",
      "filesAnalyzed": false,
      "sourceInfo": "acquired package info from go module information: /goProject",
      "licenseConcluded": "NOASSERTION",
      "licenseDeclared": "BSD-3-Clause",
      "copyrightText": "NOASSERTION",
      "externalRefs": [
        {
          "referenceCategory": "SECURITY",
          "referenceType": "cpe23Type",
          "referenceLocator": "cpe:2.3:a:golang:go:1.18.1:-:*:*:*:*:*:*"
        },
        {
          "referenceCategory": "PACKAGE-MANAGER",
          "referenceType": "purl",
          "referenceLocator": "pkg:golang/stdlib@1.18.1"
        }
      ]
    },
    {
      "name": "Order-Food",
      "SPDXID": "SPDXRef-DocumentRoot-Directory-Order-Food",
      "supplier": "NOASSERTION",
      "downloadLocation": "NOASSERTION",
      "filesAnalyzed": false,
      "primaryPackagePurpose": "FILE"
    }
  ],
  "files": [
    {
      "fileName": "/go.mod",
      "SPDXID": "SPDXRef-File-go.mod-3fc5a8d3d86e9790",
      "checksums": [
        {
          "algorithm": "SHA1",
          "checksumValue": "0000000000000000000000000000000000000000"
        }
      ],
      "licenseConcluded": "NOASSERTION",
      "copyrightText": ""
    },
    {
      "fileName": "/goProject",
      "SPDXID": "SPDXRef-File-goProject-d0f6b4d25b0787fb",
      "checksums": [
        {
          "algorithm": "SHA1",
          "checksumValue": "0000000000000000000000000000000000000000"
        }
      ],
      "licenseConcluded": "NOASSERTION",
      "copyrightText": ""
    },
    {
      "fileName": "/spdx-sbom-generator",
      "SPDXID": "SPDXRef-File-spdx-sbom-generator-c79cb16e092e22b7",
      "checksums": [
        {
          "algorithm": "SHA1",
          "checksumValue": "0000000000000000000000000000000000000000"
        }
      ],
      "licenseConcluded": "NOASSERTION",
      "copyrightText": ""
    }
  ],
  "relationships": [
    {
      "spdxElementId": "SPDXRef-Package-go-module-github.com-go-git-gcfg-006ca919669e745e",
      "relatedSpdxElement": "SPDXRef-File-spdx-sbom-generator-c79cb16e092e22b7",
      "relationshipType": "OTHER",
      "comment": "evident-by: indicates the package's existence is evident by the given file"
    },
    {
      "spdxElementId": "SPDXRef-Package-go-module-github.com-shogo82148-go-shuffle-02ae862873d6521b",
      "relatedSpdxElement": "SPDXRef-File-spdx-sbom-generator-c79cb16e092e22b7",
      "relationshipType": "OTHER",
      "comment": "evident-by: indicates the package's existence is evident by the given file"
    },
    {
      "spdxElementId": "SPDXRef-Package-go-module-github.com-shurcooL-sanitized-anchor-name-0865d03729cd7ea5",
      "relatedSpdxElement": "SPDXRef-File-spdx-sbom-generator-c79cb16e092e22b7",
      "relationshipType": "OTHER",
      "comment": "evident-by: indicates the package's existence is evident by the given file"
    },
    {
      "spdxElementId": "SPDXRef-Package-go-module-golang.org-x-text-08717222b39fbd54",
      "relatedSpdxElement": "SPDXRef-File-spdx-sbom-generator-c79cb16e092e22b7",
      "relationshipType": "OTHER",
      "comment": "evident-by: indicates the package's existence is evident by the given file"
    },
    {
      "spdxElementId": "SPDXRef-Package-go-module-github.com-gorilla-mux-262a6f49c345087c",
      "relatedSpdxElement": "SPDXRef-File-go.mod-3fc5a8d3d86e9790",
      "relationshipType": "OTHER",
      "comment": "evident-by: indicates the package's existence is evident by the given file"
    },
    {
      "spdxElementId": "SPDXRef-Package-go-module-github.com-go-enry-go-license-detector-v4-281d2e026f79d598",
      "relatedSpdxElement": "SPDXRef-File-spdx-sbom-generator-c79cb16e092e22b7",
      "relationshipType": "OTHER",
      "comment": "evident-by: indicates the package's existence is evident by the given file"
    },
    {
      "spdxElementId": "SPDXRef-Package-go-module-github.com-spf13-pflag-2c0d2f578cfd75ad",
      "relatedSpdxElement": "SPDXRef-File-spdx-sbom-generator-c79cb16e092e22b7",
      "relationshipType": "OTHER",
      "comment": "evident-by: indicates the package's existence is evident by the given file"
    },
    {
      "spdxElementId": "SPDXRef-Package-go-module-github.com-xanzy-ssh-agent-326f578af4718053",
      "relatedSpdxElement": "SPDXRef-File-spdx-sbom-generator-c79cb16e092e22b7",
      "relationshipType": "OTHER",
      "comment": "evident-by: indicates the package's existence is evident by the given file"
    },
    {
      "spdxElementId": "SPDXRef-Package-go-module-github.com-mitchellh-go-homedir-34ce0104f9648738",
      "relatedSpdxElement": "SPDXRef-File-spdx-sbom-generator-c79cb16e092e22b7",
      "relationshipType": "OTHER",
      "comment": "evident-by: indicates the package's existence is evident by the given file"
    },
    {
      "spdxElementId": "SPDXRef-Package-go-module-github.com-google-uuid-34d87e640a660224",
      "relatedSpdxElement": "SPDXRef-File-spdx-sbom-generator-c79cb16e092e22b7",
      "relationshipType": "OTHER",
      "comment": "evident-by: indicates the package's existence is evident by the given file"
    },
    {
      "spdxElementId": "SPDXRef-Package-go-module-github.com-sirupsen-logrus-430a03d7f3ae0782",
      "relatedSpdxElement": "SPDXRef-File-spdx-sbom-generator-c79cb16e092e22b7",
      "relationshipType": "OTHER",
      "comment": "evident-by: indicates the package's existence is evident by the given file"
    },
    {
      "spdxElementId": "SPDXRef-Package-go-module-stdlib-57ad8100ec4e1576",
      "relatedSpdxElement": "SPDXRef-File-goProject-d0f6b4d25b0787fb",
      "relationshipType": "OTHER",
      "comment": "evident-by: indicates the package's existence is evident by the given file"
    },
    {
      "spdxElementId": "SPDXRef-Package-go-module-github.com-kevinburke-ssh-config-5a02a9e1a3a903c2",
      "relatedSpdxElement": "SPDXRef-File-spdx-sbom-generator-c79cb16e092e22b7",
      "relationshipType": "OTHER",
      "comment": "evident-by: indicates the package's existence is evident by the given file"
    },
    {
      "spdxElementId": "SPDXRef-Package-go-module-github.com-go-git-go-billy-v5-5f54f6662b30641b",
      "relatedSpdxElement": "SPDXRef-File-spdx-sbom-generator-c79cb16e092e22b7",
      "relationshipType": "OTHER",
      "comment": "evident-by: indicates the package's existence is evident by the given file"
    },
    {
      "spdxElementId": "SPDXRef-Package-go-module-github.com-emirpasic-gods-620854f412d13680",
      "relatedSpdxElement": "SPDXRef-File-spdx-sbom-generator-c79cb16e092e22b7",
      "relationshipType": "OTHER",
      "comment": "evident-by: indicates the package's existence is evident by the given file"
    },
    {
      "spdxElementId": "SPDXRef-Package-go-module-github.com-spf13-cobra-681f517529653d5c",
      "relatedSpdxElement": "SPDXRef-File-spdx-sbom-generator-c79cb16e092e22b7",
      "relationshipType": "OTHER",
      "comment": "evident-by: indicates the package's existence is evident by the given file"
    },
    {
      "spdxElementId": "SPDXRef-Package-go-module-golang.org-x-sys-735078e5f86246b0",
      "relatedSpdxElement": "SPDXRef-File-spdx-sbom-generator-c79cb16e092e22b7",
      "relationshipType": "OTHER",
      "comment": "evident-by: indicates the package's existence is evident by the given file"
    },
    {
      "spdxElementId": "SPDXRef-Package-go-module-golang.org-x-net-861d0f1c98cedfc8",
      "relatedSpdxElement": "SPDXRef-File-spdx-sbom-generator-c79cb16e092e22b7",
      "relationshipType": "OTHER",
      "comment": "evident-by: indicates the package's existence is evident by the given file"
    },
    {
      "spdxElementId": "SPDXRef-Package-go-module-github.com-sergi-go-diff-8a86c996523c22af",
      "relatedSpdxElement": "SPDXRef-File-spdx-sbom-generator-c79cb16e092e22b7",
      "relationshipType": "OTHER",
      "comment": "evident-by: indicates the package's existence is evident by the given file"
    },
    {
      "spdxElementId": "SPDXRef-Package-go-module-github.com-imdario-mergo-8c011446289cf572",
      "relatedSpdxElement": "SPDXRef-File-spdx-sbom-generator-c79cb16e092e22b7",
      "relationshipType": "OTHER",
      "comment": "evident-by: indicates the package's existence is evident by the given file"
    },
    {
      "spdxElementId": "SPDXRef-Package-go-module-golang.org-x-crypto-993511094aee627b",
      "relatedSpdxElement": "SPDXRef-File-spdx-sbom-generator-c79cb16e092e22b7",
      "relationshipType": "OTHER",
      "comment": "evident-by: indicates the package's existence is evident by the given file"
    },
    {
      "spdxElementId": "SPDXRef-Package-go-module-gonum.org-v1-gonum-9b38fa3d8d7e4329",
      "relatedSpdxElement": "SPDXRef-File-spdx-sbom-generator-c79cb16e092e22b7",
      "relationshipType": "OTHER",
      "comment": "evident-by: indicates the package's existence is evident by the given file"
    },
    {
      "spdxElementId": "SPDXRef-Package-go-module-github.com-vifraa-gopom-9bba428b329e73c0",
      "relatedSpdxElement": "SPDXRef-File-spdx-sbom-generator-c79cb16e092e22b7",
      "relationshipType": "OTHER",
      "comment": "evident-by: indicates the package's existence is evident by the given file"
    },
    {
      "spdxElementId": "SPDXRef-Package-go-module-stdlib-9d1e6fab90778ac1",
      "relatedSpdxElement": "SPDXRef-File-spdx-sbom-generator-c79cb16e092e22b7",
      "relationshipType": "OTHER",
      "comment": "evident-by: indicates the package's existence is evident by the given file"
    },
    {
      "spdxElementId": "SPDXRef-Package-go-module-gopkg.in-neurosnap-sentences.v1-a35e8fc47f3bcc48",
      "relatedSpdxElement": "SPDXRef-File-spdx-sbom-generator-c79cb16e092e22b7",
      "relationshipType": "OTHER",
      "comment": "evident-by: indicates the package's existence is evident by the given file"
    },
    {
      "spdxElementId": "SPDXRef-Package-go-module-github.com-go-git-go-git-v5-a4e5d79c27e1958e",
      "relatedSpdxElement": "SPDXRef-File-spdx-sbom-generator-c79cb16e092e22b7",
      "relationshipType": "OTHER",
      "comment": "evident-by: indicates the package's existence is evident by the given file"
    },
    {
      "spdxElementId": "SPDXRef-Package-go-module-github.com-jdkato-prose-b92485d836034044",
      "relatedSpdxElement": "SPDXRef-File-spdx-sbom-generator-c79cb16e092e22b7",
      "relationshipType": "OTHER",
      "comment": "evident-by: indicates the package's existence is evident by the given file"
    },
    {
      "spdxElementId": "SPDXRef-Package-go-module-github.com-hhatto-gorst-c70b3f8db8382927",
      "relatedSpdxElement": "SPDXRef-File-spdx-sbom-generator-c79cb16e092e22b7",
      "relationshipType": "OTHER",
      "comment": "evident-by: indicates the package's existence is evident by the given file"
    },
    {
      "spdxElementId": "SPDXRef-Package-go-module-spdx-sbom-generator-d0a2de88739abf02",
      "relatedSpdxElement": "SPDXRef-File-spdx-sbom-generator-c79cb16e092e22b7",
      "relationshipType": "OTHER",
      "comment": "evident-by: indicates the package's existence is evident by the given file"
    },
    {
      "spdxElementId": "SPDXRef-Package-go-module-github.com-jbenet-go-context-d447fb06434976d8",
      "relatedSpdxElement": "SPDXRef-File-spdx-sbom-generator-c79cb16e092e22b7",
      "relationshipType": "OTHER",
      "comment": "evident-by: indicates the package's existence is evident by the given file"
    },
    {
      "spdxElementId": "SPDXRef-Package-go-module-github.com-ekzhu-minhash-lsh-d5879d3235e12b2a",
      "relatedSpdxElement": "SPDXRef-File-spdx-sbom-generator-c79cb16e092e22b7",
      "relationshipType": "OTHER",
      "comment": "evident-by: indicates the package's existence is evident by the given file"
    },
    {
      "spdxElementId": "SPDXRef-Package-go-module-github.com-montanaflynn-stats-d91fed62197fca1c",
      "relatedSpdxElement": "SPDXRef-File-spdx-sbom-generator-c79cb16e092e22b7",
      "relationshipType": "OTHER",
      "comment": "evident-by: indicates the package's existence is evident by the given file"
    },
    {
      "spdxElementId": "SPDXRef-Package-go-module-gopkg.in-warnings.v0-e924fe56aa559902",
      "relatedSpdxElement": "SPDXRef-File-spdx-sbom-generator-c79cb16e092e22b7",
      "relationshipType": "OTHER",
      "comment": "evident-by: indicates the package's existence is evident by the given file"
    },
    {
      "spdxElementId": "SPDXRef-Package-go-module-github.com-pkg-errors-ea692f11be449967",
      "relatedSpdxElement": "SPDXRef-File-spdx-sbom-generator-c79cb16e092e22b7",
      "relationshipType": "OTHER",
      "comment": "evident-by: indicates the package's existence is evident by the given file"
    },
    {
      "spdxElementId": "SPDXRef-Package-go-module-github.com-russross-blackfriday-v2-ef70a7c214258c18",
      "relatedSpdxElement": "SPDXRef-File-spdx-sbom-generator-c79cb16e092e22b7",
      "relationshipType": "OTHER",
      "comment": "evident-by: indicates the package's existence is evident by the given file"
    },
    {
      "spdxElementId": "SPDXRef-Package-go-module-goProject-eff3e671e31c66c7",
      "relatedSpdxElement": "SPDXRef-File-goProject-d0f6b4d25b0787fb",
      "relationshipType": "OTHER",
      "comment": "evident-by: indicates the package's existence is evident by the given file"
    },
    {
      "spdxElementId": "SPDXRef-Package-go-module-golang.org-x-exp-f09380142cf00a77",
      "relatedSpdxElement": "SPDXRef-File-spdx-sbom-generator-c79cb16e092e22b7",
      "relationshipType": "OTHER",
      "comment": "evident-by: indicates the package's existence is evident by the given file"
    },
    {
      "spdxElementId": "SPDXRef-Package-go-module-github.com-dgryski-go-minhash-f235105d189336dc",
      "relatedSpdxElement": "SPDXRef-File-spdx-sbom-generator-c79cb16e092e22b7",
      "relationshipType": "OTHER",
      "comment": "evident-by: indicates the package's existence is evident by the given file"
    },
    {
      "spdxElementId": "SPDXRef-DocumentRoot-Directory-Order-Food",
      "relatedSpdxElement": "SPDXRef-Package-go-module-github.com-dgryski-go-minhash-f235105d189336dc",
      "relationshipType": "CONTAINS"
    },
    {
      "spdxElementId": "SPDXRef-DocumentRoot-Directory-Order-Food",
      "relatedSpdxElement": "SPDXRef-Package-go-module-github.com-ekzhu-minhash-lsh-d5879d3235e12b2a",
      "relationshipType": "CONTAINS"
    },
    {
      "spdxElementId": "SPDXRef-DocumentRoot-Directory-Order-Food",
      "relatedSpdxElement": "SPDXRef-Package-go-module-github.com-emirpasic-gods-620854f412d13680",
      "relationshipType": "CONTAINS"
    },
    {
      "spdxElementId": "SPDXRef-DocumentRoot-Directory-Order-Food",
      "relatedSpdxElement": "SPDXRef-Package-go-module-github.com-go-enry-go-license-detector-v4-281d2e026f79d598",
      "relationshipType": "CONTAINS"
    },
    {
      "spdxElementId": "SPDXRef-DocumentRoot-Directory-Order-Food",
      "relatedSpdxElement": "SPDXRef-Package-go-module-github.com-go-git-gcfg-006ca919669e745e",
      "relationshipType": "CONTAINS"
    },
    {
      "spdxElementId": "SPDXRef-DocumentRoot-Directory-Order-Food",
      "relatedSpdxElement": "SPDXRef-Package-go-module-github.com-go-git-go-billy-v5-5f54f6662b30641b",
      "relationshipType": "CONTAINS"
    },
    {
      "spdxElementId": "SPDXRef-DocumentRoot-Directory-Order-Food",
      "relatedSpdxElement": "SPDXRef-Package-go-module-github.com-go-git-go-git-v5-a4e5d79c27e1958e",
      "relationshipType": "CONTAINS"
    },
    {
      "spdxElementId": "SPDXRef-DocumentRoot-Directory-Order-Food",
      "relatedSpdxElement": "SPDXRef-Package-go-module-github.com-google-uuid-34d87e640a660224",
      "relationshipType": "CONTAINS"
    },
    {
      "spdxElementId": "SPDXRef-DocumentRoot-Directory-Order-Food",
      "relatedSpdxElement": "SPDXRef-Package-go-module-github.com-gorilla-mux-262a6f49c345087c",
      "relationshipType": "CONTAINS"
    },
    {
      "spdxElementId": "SPDXRef-DocumentRoot-Directory-Order-Food",
      "relatedSpdxElement": "SPDXRef-Package-go-module-github.com-hhatto-gorst-c70b3f8db8382927",
      "relationshipType": "CONTAINS"
    },
    {
      "spdxElementId": "SPDXRef-DocumentRoot-Directory-Order-Food",
      "relatedSpdxElement": "SPDXRef-Package-go-module-github.com-imdario-mergo-8c011446289cf572",
      "relationshipType": "CONTAINS"
    },
    {
      "spdxElementId": "SPDXRef-DocumentRoot-Directory-Order-Food",
      "relatedSpdxElement": "SPDXRef-Package-go-module-github.com-jbenet-go-context-d447fb06434976d8",
      "relationshipType": "CONTAINS"
    },
    {
      "spdxElementId": "SPDXRef-DocumentRoot-Directory-Order-Food",
      "relatedSpdxElement": "SPDXRef-Package-go-module-github.com-jdkato-prose-b92485d836034044",
      "relationshipType": "CONTAINS"
    },
    {
      "spdxElementId": "SPDXRef-DocumentRoot-Directory-Order-Food",
      "relatedSpdxElement": "SPDXRef-Package-go-module-github.com-kevinburke-ssh-config-5a02a9e1a3a903c2",
      "relationshipType": "CONTAINS"
    },
    {
      "spdxElementId": "SPDXRef-DocumentRoot-Directory-Order-Food",
      "relatedSpdxElement": "SPDXRef-Package-go-module-github.com-mitchellh-go-homedir-34ce0104f9648738",
      "relationshipType": "CONTAINS"
    },
    {
      "spdxElementId": "SPDXRef-DocumentRoot-Directory-Order-Food",
      "relatedSpdxElement": "SPDXRef-Package-go-module-github.com-montanaflynn-stats-d91fed62197fca1c",
      "relationshipType": "CONTAINS"
    },
    {
      "spdxElementId": "SPDXRef-DocumentRoot-Directory-Order-Food",
      "relatedSpdxElement": "SPDXRef-Package-go-module-github.com-pkg-errors-ea692f11be449967",
      "relationshipType": "CONTAINS"
    },
    {
      "spdxElementId": "SPDXRef-DocumentRoot-Directory-Order-Food",
      "relatedSpdxElement": "SPDXRef-Package-go-module-github.com-russross-blackfriday-v2-ef70a7c214258c18",
      "relationshipType": "CONTAINS"
    },
    {
      "spdxElementId": "SPDXRef-DocumentRoot-Directory-Order-Food",
      "relatedSpdxElement": "SPDXRef-Package-go-module-github.com-sergi-go-diff-8a86c996523c22af",
      "relationshipType": "CONTAINS"
    },
    {
      "spdxElementId": "SPDXRef-DocumentRoot-Directory-Order-Food",
      "relatedSpdxElement": "SPDXRef-Package-go-module-github.com-shogo82148-go-shuffle-02ae862873d6521b",
      "relationshipType": "CONTAINS"
    },
    {
      "spdxElementId": "SPDXRef-DocumentRoot-Directory-Order-Food",
      "relatedSpdxElement": "SPDXRef-Package-go-module-github.com-shurcooL-sanitized-anchor-name-0865d03729cd7ea5",
      "relationshipType": "CONTAINS"
    },
    {
      "spdxElementId": "SPDXRef-DocumentRoot-Directory-Order-Food",
      "relatedSpdxElement": "SPDXRef-Package-go-module-github.com-sirupsen-logrus-430a03d7f3ae0782",
      "relationshipType": "CONTAINS"
    },
    {
      "spdxElementId": "SPDXRef-DocumentRoot-Directory-Order-Food",
      "relatedSpdxElement": "SPDXRef-Package-go-module-github.com-spf13-cobra-681f517529653d5c",
      "relationshipType": "CONTAINS"
    },
    {
      "spdxElementId": "SPDXRef-DocumentRoot-Directory-Order-Food",
      "relatedSpdxElement": "SPDXRef-Package-go-module-github.com-spf13-pflag-2c0d2f578cfd75ad",
      "relationshipType": "CONTAINS"
    },
    {
      "spdxElementId": "SPDXRef-DocumentRoot-Directory-Order-Food",
      "relatedSpdxElement": "SPDXRef-Package-go-module-github.com-vifraa-gopom-9bba428b329e73c0",
      "relationshipType": "CONTAINS"
    },
    {
      "spdxElementId": "SPDXRef-DocumentRoot-Directory-Order-Food",
      "relatedSpdxElement": "SPDXRef-Package-go-module-github.com-xanzy-ssh-agent-326f578af4718053",
      "relationshipType": "CONTAINS"
    },
    {
      "spdxElementId": "SPDXRef-DocumentRoot-Directory-Order-Food",
      "relatedSpdxElement": "SPDXRef-Package-go-module-goProject-eff3e671e31c66c7",
      "relationshipType": "CONTAINS"
    },
    {
      "spdxElementId": "SPDXRef-DocumentRoot-Directory-Order-Food",
      "relatedSpdxElement": "SPDXRef-Package-go-module-golang.org-x-crypto-993511094aee627b",
      "relationshipType": "CONTAINS"
    },
    {
      "spdxElementId": "SPDXRef-DocumentRoot-Directory-Order-Food",
      "relatedSpdxElement": "SPDXRef-Package-go-module-golang.org-x-exp-f09380142cf00a77",
      "relationshipType": "CONTAINS"
    },
    {
      "spdxElementId": "SPDXRef-DocumentRoot-Directory-Order-Food",
      "relatedSpdxElement": "SPDXRef-Package-go-module-golang.org-x-net-861d0f1c98cedfc8",
      "relationshipType": "CONTAINS"
    },
    {
      "spdxElementId": "SPDXRef-DocumentRoot-Directory-Order-Food",
      "relatedSpdxElement": "SPDXRef-Package-go-module-golang.org-x-sys-735078e5f86246b0",
      "relationshipType": "CONTAINS"
    },
    {
      "spdxElementId": "SPDXRef-DocumentRoot-Directory-Order-Food",
      "relatedSpdxElement": "SPDXRef-Package-go-module-golang.org-x-text-08717222b39fbd54",
      "relationshipType": "CONTAINS"
    },
    {
      "spdxElementId": "SPDXRef-DocumentRoot-Directory-Order-Food",
      "relatedSpdxElement": "SPDXRef-Package-go-module-gonum.org-v1-gonum-9b38fa3d8d7e4329",
      "relationshipType": "CONTAINS"
    },
    {
      "spdxElementId": "SPDXRef-DocumentRoot-Directory-Order-Food",
      "relatedSpdxElement": "SPDXRef-Package-go-module-gopkg.in-neurosnap-sentences.v1-a35e8fc47f3bcc48",
      "relationshipType": "CONTAINS"
    },
    {
      "spdxElementId": "SPDXRef-DocumentRoot-Directory-Order-Food",
      "relatedSpdxElement": "SPDXRef-Package-go-module-gopkg.in-warnings.v0-e924fe56aa559902",
      "relationshipType": "CONTAINS"
    },
    {
      "spdxElementId": "SPDXRef-DocumentRoot-Directory-Order-Food",
      "relatedSpdxElement": "SPDXRef-Package-go-module-spdx-sbom-generator-d0a2de88739abf02",
      "relationshipType": "CONTAINS"
    },
    {
      "spdxElementId": "SPDXRef-DocumentRoot-Directory-Order-Food",
      "relatedSpdxElement": "SPDXRef-Package-go-module-stdlib-9d1e6fab90778ac1",
      "relationshipType": "CONTAINS"
    },
    {
      "spdxElementId": "SPDXRef-DocumentRoot-Directory-Order-Food",
      "relatedSpdxElement": "SPDXRef-Package-go-module-stdlib-57ad8100ec4e1576",
      "relationshipType": "CONTAINS"
    },
    {
      "spdxElementId": "SPDXRef-DOCUMENT",
      "relatedSpdxElement": "SPDXRef-DocumentRoot-Directory-Order-Food",
      "relationshipType": "DESCRIBES"
    }
  ]
}
